pytorch_damn/__init__.py
pytorch_damn/__main__.py
pytorch_damn/dataset.py
pytorch_damn/model.py
pytorch_damn/examples/__init__.py
pytorch_damn/examples/domain_adaptation.py
pytorch_damn-0.6.4.dist-info/METADATA
pytorch_damn-0.6.4.dist-info/WHEEL
pytorch_damn-0.6.4.dist-info/top_level.txt
pytorch_damn-0.6.4.dist-info/RECORD
