Metadata-Version: 2.1
Name: pytorch-damn
Version: 0.6.4
Summary: Domain Attention Mixing Network: tool for domain adaptation
Home-page: https://github.com/tilkb/damn
Author: Bence Tilk
Author-email: bence.tilk@gmail.com
License: UNKNOWN
Platform: UNKNOWN
Classifier: Programming Language :: Python :: 3
Classifier: License :: OSI Approved :: MIT License
Classifier: Operating System :: OS Independent
Requires-Python: >=3.6
Requires-Dist: torch
Requires-Dist: pytorch-lightning
Requires-Dist: torchvision
